erys-0.2.10.dist-info/licenses/LICENSE
src/__init__.py
src/app.py
src/cell.py
src/code_cell.py
src/exec_queue.py
src/file.py
src/markdown_cell.py
src/notebook.py
src/notebook_kernel.py
src/save_as_screen.py
src/styles.tcss
erys-0.2.10.dist-info/METADATA
erys-0.2.10.dist-info/WHEEL
erys-0.2.10.dist-info/entry_points.txt
erys-0.2.10.dist-info/top_level.txt
erys-0.2.10.dist-info/RECORD
