Metadata-Version: 2.4
Name: erys
Version: 0.2.10
Summary: Terminal interface for creating, editing, and running Jupyter Notebook
Author: Nathnael (Nati) Bekele
Maintainer: Nathnael (Nati) Bekele
License-Expression: Apache-2.0
Project-URL: Homepage, https://github.com/natibek/erys
Project-URL: Repository, https://github.com/natibek/erys
Project-URL: Issues, https://github.com/natibek/erys/issues
Project-URL: Readme, https://github.com/natibek/erys/blob/main/README.md
Project-URL: Changelog, https://github.com/natibek/erys/blob/main/CHANGELOG
Keywords: jupyter notebook,terminal,textual,notebook,python,tui
Classifier: Programming Language :: Python :: 3.10
Classifier: Programming Language :: Python :: 3.11
Classifier: Programming Language :: Python :: 3.12
Classifier: Programming Language :: Python :: 3.13
Classifier: Operating System :: POSIX :: Linux
Classifier: Operating System :: MacOS
Classifier: Topic :: Text Editors
Classifier: Topic :: Terminals
Requires-Python: >=3.10
License-File: LICENSE
Requires-Dist: textual[syntax]==6.2.1
Requires-Dist: tree-sitter==0.25.2
Requires-Dist: tree-sitter-python==0.25.0
Requires-Dist: ipykernel==6.30.1
Requires-Dist: pyperclip==1.9.0
Requires-Dist: jupyter_client==8.6.3
Requires-Dist: pillow==11.3.0
Dynamic: license-file
